tracwikicss/__init__.py
tracwikicss/plugin.py
TracWikiCssPlugin-0.3.1.dist-info/METADATA
TracWikiCssPlugin-0.3.1.dist-info/WHEEL
TracWikiCssPlugin-0.3.1.dist-info/entry_points.txt
TracWikiCssPlugin-0.3.1.dist-info/top_level.txt
TracWikiCssPlugin-0.3.1.dist-info/RECORD
