Metadata-Version: 2.1
Name: TracWikiCssPlugin
Version: 0.3.1
Summary: Wiki pages as CSS files Trac Plugin.
Home-page: https://www.trac-hacks.org/wiki/WikiCssPlugin
Author: Martin Scharrer
Author-email: martin@scharrer-online.de
License: GPLv3
Keywords: trac plugin wiki css
Platform: UNKNOWN
Classifier: Framework :: Trac
Requires-Dist: Trac
